glootil/__init__.py
glootil-0.2.5.dist-info/licenses/LICENSE
glootil-0.2.5.dist-info/METADATA
glootil-0.2.5.dist-info/WHEEL
glootil-0.2.5.dist-info/top_level.txt
glootil-0.2.5.dist-info/RECORD
