Metadata-Version: 2.4
Name: glootil
Version: 0.2.5
Summary: Library to build Gloodata extensions
Author-email: Mariano Guerra <mariano@gloodata.com>
License-Expression: MIT
Project-URL: Homepage, https://github.com/gloodata/glootil-py
Project-URL: Issues, https://github.com/gloodata/glootil-py/issues
Requires-Python: >=3.10
License-File: LICENSE
Dynamic: license-file
